eve_peewee/__init__.py
eve_peewee-0.0.6.dist-info/DESCRIPTION.rst
eve_peewee-0.0.6.dist-info/METADATA
eve_peewee-0.0.6.dist-info/RECORD
eve_peewee-0.0.6.dist-info/WHEEL
eve_peewee-0.0.6.dist-info/metadata.json
eve_peewee-0.0.6.dist-info/top_level.txt
