Metadata-Version: 2.0
Name: eve-peewee
Version: 0.0.6
Summary: Data layer for Eve powered by peewee.
Home-page: https://github.com/stt/eve-peewee
Author: Samuli Tuomola
Author-email: samuli.tuomola@gmail.com
License: BSD
Platform: any
Classifier: Development Status :: 3 - Alpha
Classifier: Environment :: Web Environment
Classifier: Intended Audience :: Developers
Classifier: License :: OSI Approved :: BSD License
Classifier: Operating System :: OS Independent
Classifier: Programming Language :: Python
Classifier: Programming Language :: Python :: 2
Classifier: Programming Language :: Python :: 2.6
Classifier: Programming Language :: Python :: 2.7
Classifier: Programming Language :: Python :: 3
Classifier: Programming Language :: Python :: 3.3
Classifier: Programming Language :: Python :: 3.4
Classifier: Topic :: Internet :: WWW/HTTP :: Dynamic Content
Requires-Dist: Eve (>=0.6)
Requires-Dist: peewee (>=2.8)
Provides-Extra: test
